krtc/__init__.py
krtc/_version.py
krtc/cmpauth.py
krtc/krtc.py
krtc/version.py
krtc/tests/__init__.py
krtc/tests/test_kerberos.py
lcls_krtc-0.3.1.dist-info/licenses/AUTHORS.rst
lcls_krtc-0.3.1.dist-info/licenses/LICENSE
lcls_krtc-0.3.1.dist-info/METADATA
lcls_krtc-0.3.1.dist-info/WHEEL
lcls_krtc-0.3.1.dist-info/top_level.txt
lcls_krtc-0.3.1.dist-info/RECORD
